batch_rpc_provider/__init__.py
batch_rpc_provider/_version.py
batch_rpc_provider/batch_rpc_provider.py
batch_rpc_provider/history_checks.py
batch_rpc_provider/utils.py
batch_rpc_provider-1.2.1.data/scripts/__init__.py
batch_rpc_provider-1.2.1.data/scripts/batch_rpc_provider.py
batch_rpc_provider-1.2.1.dist-info/LICENSE
batch_rpc_provider-1.2.1.dist-info/METADATA
batch_rpc_provider-1.2.1.dist-info/WHEEL
batch_rpc_provider-1.2.1.dist-info/top_level.txt
batch_rpc_provider-1.2.1.dist-info/RECORD
